graphene_django_cud/__init__.py
graphene_django_cud/consts.py
graphene_django_cud/converter.py
graphene_django_cud/registry.py
graphene_django_cud/string_util.py
graphene_django_cud/types.py
graphene_django_cud/urls.py
graphene_django_cud/wsgi.py
graphene_django_cud/mutations/__init__.py
graphene_django_cud/mutations/batch_create.py
graphene_django_cud/mutations/batch_delete.py
graphene_django_cud/mutations/batch_patch.py
graphene_django_cud/mutations/batch_update.py
graphene_django_cud/mutations/core.py
graphene_django_cud/mutations/create.py
graphene_django_cud/mutations/delete.py
graphene_django_cud/mutations/filter_delete.py
graphene_django_cud/mutations/filter_update.py
graphene_django_cud/mutations/patch.py
graphene_django_cud/mutations/update.py
graphene_django_cud/tests/__init__.py
graphene_django_cud/tests/dummy_query.py
graphene_django_cud/tests/factories.py
graphene_django_cud/tests/models.py
graphene_django_cud/tests/schema.py
graphene_django_cud/tests/test_batch_create_mutation.py
graphene_django_cud/tests/test_batch_delete_mutation.py
graphene_django_cud/tests/test_batch_patch_mutation.py
graphene_django_cud/tests/test_batch_update_mutation.py
graphene_django_cud/tests/test_converter.py
graphene_django_cud/tests/test_create_mutation.py
graphene_django_cud/tests/test_delete_mutation.py
graphene_django_cud/tests/test_filter_delete_mutation.py
graphene_django_cud/tests/test_filter_update_mutation.py
graphene_django_cud/tests/test_patch_mutation.py
graphene_django_cud/tests/test_update_mutation.py
graphene_django_cud/tests/test_util.py
graphene_django_cud/tests/urls.py
graphene_django_cud/tests/migrations/0001_initial.py
graphene_django_cud/tests/migrations/0002_dog_tag.py
graphene_django_cud/tests/migrations/0003_dog_breed.py
graphene_django_cud/tests/migrations/0004_mouse_keeper.py
graphene_django_cud/tests/migrations/0005_dogregistration.py
graphene_django_cud/tests/migrations/0006_dog_bark_count.py
graphene_django_cud-0.13.0.dist-info/LICENSE.md
graphene_django_cud-0.13.0.dist-info/METADATA
graphene_django_cud-0.13.0.dist-info/WHEEL
graphene_django_cud-0.13.0.dist-info/top_level.txt
graphene_django_cud-0.13.0.dist-info/RECORD
