Metadata-Version: 2.1
Name: graphene-django-cud
Version: 0.13.0
Summary: Create, update and delete mutations for graphene-django
Home-page: https://github.com/tOgg1/graphene-django-cud
Author: Tormod Haugland
Author-email: tormod.haugland@gmail.com
Classifier: Programming Language :: Python :: 3
Classifier: License :: OSI Approved :: MIT License
Classifier: Operating System :: OS Independent
License-File: LICENSE.md
Requires-Dist: graphene-django >=3.0
Requires-Dist: graphene-file-upload >=1.2
